<?xml version="1.0" encoding="utf-8"?>
<SoundBanksInfo Platform="Windows" BasePlatform="Windows" SchemaVersion="11" SoundbankVersion="120">
	<RootPaths>
		<ProjectRoot>/Users/PeteJurasek/Library/Application Support/Wwise2016/Bottles/wwise/dosdevices/y:/Documents/spacejamu/Space Jam Wwise/</ProjectRoot>
		<SourceFilesRoot>/Users/PeteJurasek/Library/Application Support/Wwise2016/Bottles/wwise/dosdevices/y:/Documents/spacejamu/Space Jam Wwise/.cache/Windows/</SourceFilesRoot>
		<SoundBanksRoot>/Users/PeteJurasek/Library/Application Support/Wwise2016/Bottles/wwise/dosdevices/y:/Documents/spacejamu/Space Jam Wwise/GeneratedSoundBanks/Windows/</SoundBanksRoot>
		<ExternalSourcesInputFile></ExternalSourcesInputFile>
		<ExternalSourcesOutputRoot>/Users/PeteJurasek/Library/Application Support/Wwise2016/Bottles/wwise/dosdevices/y:/Documents/spacejamu/Space Jam Wwise/GeneratedSoundBanks/Windows/</ExternalSourcesOutputRoot>
	</RootPaths>
	<DialogueEvents/>
	<StreamedFiles/>
	<MediaFilesNotInAnyBank/>
	<SoundBanks>
		<SoundBank Id="534561221" Language="SFX">
			<ObjectPath>\SoundBanks\Default Work Unit\MainSoundbank</ObjectPath>
			<ShortName>MainSoundbank</ShortName>
			<Path>MainSoundbank.bnk</Path>
			<IncludedEvents>
				<Event Id="1866025847" Name="Footstep" ObjectPath="\Events\Default Work Unit\Footstep" MaxAttenuation="100.000000"/>
				<Event Id="1952003650" Name="IceAmbience" ObjectPath="\Events\Default Work Unit\IceAmbience"/>
				<Event Id="3982605422" Name="Laser" ObjectPath="\Events\Default Work Unit\Laser"/>
				<Event Id="324443136" Name="Pistol" ObjectPath="\Events\Default Work Unit\Pistol"/>
				<Event Id="417627684" Name="PlayMusic" ObjectPath="\Events\Default Work Unit\PlayMusic"/>
				<Event Id="3812882407" Name="RainAmbience" ObjectPath="\Events\Default Work Unit\RainAmbience"/>
				<Event Id="693161857" Name="ShadowAmbience" ObjectPath="\Events\Default Work Unit\ShadowAmbience"/>
				<Event Id="51683977" Name="Shotgun" ObjectPath="\Events\Default Work Unit\Shotgun"/>
			</IncludedEvents>
			<IncludedMemoryFiles>
				<File Id="161480498" Language="SFX">
					<ShortName>LaserBeam1.wav</ShortName>
					<Path>SFX/LaserBeam1_9E69E797.wem</Path>
				</File>
				<File Id="172787058" Language="SFX">
					<ShortName>ambience5.wav</ShortName>
					<Path>SFX/ambience5_9E69E797.wem</Path>
				</File>
				<File Id="173470816" Language="SFX">
					<ShortName>Music Stems\Seg2.wav</ShortName>
					<Path>SFX/Music Stems/Seg2_4B8CC0C5.wem</Path>
				</File>
				<File Id="207736036" Language="SFX">
					<ShortName>Music Stems\FastSeg2.wav</ShortName>
					<Path>SFX/Music Stems/FastSeg2_4B8CC0C5.wem</Path>
				</File>
				<File Id="219820858" Language="SFX">
					<ShortName>SnowFootstep3.wav</ShortName>
					<Path>SFX/SnowFootstep3_9E69E797.wem</Path>
				</File>
				<File Id="223893940" Language="SFX">
					<ShortName>Music Stems\FastSeg3.wav</ShortName>
					<Path>SFX/Music Stems/FastSeg3_4B8CC0C5.wem</Path>
				</File>
				<File Id="227970671" Language="SFX">
					<ShortName>Music Stems\FastSeg6.wav</ShortName>
					<Path>SFX/Music Stems/FastSeg6_4B8CC0C5.wem</Path>
				</File>
				<File Id="251053522" Language="SFX">
					<ShortName>SnowAmbience1.wav</ShortName>
					<Path>SFX/SnowAmbience1_9E69E797.wem</Path>
				</File>
				<File Id="271099194" Language="SFX">
					<ShortName>Music Stems\Seg3.wav</ShortName>
					<Path>SFX/Music Stems/Seg3_4B8CC0C5.wem</Path>
				</File>
				<File Id="301892138" Language="SFX">
					<ShortName>Music Stems\FastSeg1.wav</ShortName>
					<Path>SFX/Music Stems/FastSeg1_4B8CC0C5.wem</Path>
				</File>
				<File Id="316437612" Language="SFX">
					<ShortName>SnowFootstep5.wav</ShortName>
					<Path>SFX/SnowFootstep5_9E69E797.wem</Path>
				</File>
				<File Id="384060917" Language="SFX">
					<ShortName>Music Stems\FastSeg4.wav</ShortName>
					<Path>SFX/Music Stems/FastSeg4_4B8CC0C5.wem</Path>
				</File>
				<File Id="389132379" Language="SFX">
					<ShortName>ambience4.wav</ShortName>
					<Path>SFX/ambience4_9E69E797.wem</Path>
				</File>
				<File Id="407704412" Language="SFX">
					<ShortName>Music Stems\FastSeg12(outro).wav</ShortName>
					<Path>SFX/Music Stems/FastSeg12(outro)_4B8CC0C5.wem</Path>
				</File>
				<File Id="424694750" Language="SFX">
					<ShortName>ambience1.wav</ShortName>
					<Path>SFX/ambience1_9E69E797.wem</Path>
				</File>
				<File Id="425606117" Language="SFX">
					<ShortName>SnowFootstep2.wav</ShortName>
					<Path>SFX/SnowFootstep2_9E69E797.wem</Path>
				</File>
				<File Id="501188736" Language="SFX">
					<ShortName>Music Stems\FastSeg7.wav</ShortName>
					<Path>SFX/Music Stems/FastSeg7_4B8CC0C5.wem</Path>
				</File>
				<File Id="512343843" Language="SFX">
					<ShortName>ambience3.wav</ShortName>
					<Path>SFX/ambience3_9E69E797.wem</Path>
				</File>
				<File Id="541905892" Language="SFX">
					<ShortName>Music Stems\Seg1.wav</ShortName>
					<Path>SFX/Music Stems/Seg1_4B8CC0C5.wem</Path>
				</File>
				<File Id="544288642" Language="SFX">
					<ShortName>ambience8.wav</ShortName>
					<Path>SFX/ambience8_9E69E797.wem</Path>
				</File>
				<File Id="545781998" Language="SFX">
					<ShortName>LaserShotgunNoTail.wav</ShortName>
					<Path>SFX/LaserShotgunNoTail_9E69E797.wem</Path>
				</File>
				<File Id="582706071" Language="SFX">
					<ShortName>SnowAmbience3.wav</ShortName>
					<Path>SFX/SnowAmbience3_9E69E797.wem</Path>
				</File>
				<File Id="622020659" Language="SFX">
					<ShortName>SnowFootstep1.wav</ShortName>
					<Path>SFX/SnowFootstep1_9E69E797.wem</Path>
				</File>
				<File Id="637521793" Language="SFX">
					<ShortName>Rain.wav</ShortName>
					<Path>SFX/Rain_9E69E797.wem</Path>
				</File>
				<File Id="670029384" Language="SFX">
					<ShortName>SnowFootstep6.wav</ShortName>
					<Path>SFX/SnowFootstep6_9E69E797.wem</Path>
				</File>
				<File Id="764627016" Language="SFX">
					<ShortName>ambience6.wav</ShortName>
					<Path>SFX/ambience6_9E69E797.wem</Path>
				</File>
				<File Id="764758262" Language="SFX">
					<ShortName>Music Stems\FastSeg10.wav</ShortName>
					<Path>SFX/Music Stems/FastSeg10_4B8CC0C5.wem</Path>
				</File>
				<File Id="807596079" Language="SFX">
					<ShortName>LaserShotgun2.wav</ShortName>
					<Path>SFX/LaserShotgun2_9E69E797.wem</Path>
				</File>
				<File Id="838238911" Language="SFX">
					<ShortName>SnowFootstep4.wav</ShortName>
					<Path>SFX/SnowFootstep4_9E69E797.wem</Path>
				</File>
				<File Id="850928140" Language="SFX">
					<ShortName>PistolFireLaunch.wav</ShortName>
					<Path>SFX/PistolFireLaunch_9E69E797.wem</Path>
				</File>
				<File Id="856116723" Language="SFX">
					<ShortName>ambience2.wav</ShortName>
					<Path>SFX/ambience2_9E69E797.wem</Path>
				</File>
				<File Id="897623173" Language="SFX">
					<ShortName>Music Stems\FastSeg8.wav</ShortName>
					<Path>SFX/Music Stems/FastSeg8_4B8CC0C5.wem</Path>
				</File>
				<File Id="924111062" Language="SFX">
					<ShortName>Music Stems\FastSeg11.wav</ShortName>
					<Path>SFX/Music Stems/FastSeg11_4B8CC0C5.wem</Path>
				</File>
				<File Id="986579259" Language="SFX">
					<ShortName>Music Stems\Seg4.wav</ShortName>
					<Path>SFX/Music Stems/Seg4_4B8CC0C5.wem</Path>
				</File>
				<File Id="995426972" Language="SFX">
					<ShortName>Music Stems\FastSeg9.wav</ShortName>
					<Path>SFX/Music Stems/FastSeg9_4B8CC0C5.wem</Path>
				</File>
				<File Id="1030414251" Language="SFX">
					<ShortName>SnowAmbience2.wav</ShortName>
					<Path>SFX/SnowAmbience2_9E69E797.wem</Path>
				</File>
				<File Id="1059312155" Language="SFX">
					<ShortName>ambience7.wav</ShortName>
					<Path>SFX/ambience7_9E69E797.wem</Path>
				</File>
			</IncludedMemoryFiles>
		</SoundBank>
		<SoundBank Id="1355168291" Language="SFX">
			<ObjectPath>Init</ObjectPath>
			<ShortName>Init</ShortName>
			<Path>Init.bnk</Path>
		</SoundBank>
	</SoundBanks>
</SoundBanksInfo>
